cursofiap/__init__.py
cursofiap/core.py
machinelearningfiap_hirai_package-1.0.0.dist-info/METADATA
machinelearningfiap_hirai_package-1.0.0.dist-info/WHEEL
machinelearningfiap_hirai_package-1.0.0.dist-info/top_level.txt
machinelearningfiap_hirai_package-1.0.0.dist-info/RECORD
